{
  "DisplayName": "Master Workflow",
  "Tooltip": null,
  "HelpLink": null,
  "Color": null,
  "OriginalIconFileName": null,
  "Arguments": [
    {
      "Name": "credentials_Out",
      "DisplayName": "credentials_Out",
      "Category": null,
      "Tooltip": null,
      "Placeholder": null,
      "Widget": null,
      "IsRequired": false,
      "IsPrincipal": true,
      "ArgumentType": 0,
      "DataSourceItems": null
    },
    {
      "Name": "excel_FilePath_Out",
      "DisplayName": "excel_FilePath_Out",
      "Category": null,
      "Tooltip": null,
      "Placeholder": null,
      "Widget": null,
      "IsRequired": false,
      "IsPrincipal": true,
      "ArgumentType": 0,
      "DataSourceItems": null
    },
    {
      "Name": "emailRecipient_In",
      "DisplayName": "emailRecipient_In",
      "Category": null,
      "Tooltip": null,
      "Placeholder": "csendes mód",
      "Widget": null,
      "IsRequired": false,
      "IsPrincipal": true,
      "ArgumentType": 0,
      "DataSourceItems": null
    },
    {
      "Name": "robotEmail_frissites_In",
      "DisplayName": "robotEmail_frissites_In",
      "Category": null,
      "Tooltip": null,
      "Placeholder": "True",
      "Widget": null,
      "IsRequired": false,
      "IsPrincipal": true,
      "ArgumentType": 0,
      "DataSourceItems": null
    }
  ]
}